vhdl1/fm.vhdl
library ieee;
use ieee.std_logic_1164.all;

entity full_adder is
    port (
        a, b, cin : in  std_logic;
        sum, cout : out std_logic
    );
end full_adder;

architecture behavioral of full_adder is
begin
    sum <= (a xor b) xor cin;
    cout <= (a and b) or ((a xor b) and cin);
end behavioral;

vhdl1/fa_tb.vhdl
library ieee;
use ieee.std_logic_1164.all;

entity full_adder_tb is
end full_adder_tb;

architecture behavioral of full_adder_tb is
    component full_adder
        port (
            a, b, cin : in  std_logic;
            sum, cout : out std_logic
        );
    end component;

    signal a, b, cin : std_logic;
    signal sum, cout : std_logic;

begin
    uut: full_adder port map (
        a => a,
        b => b,
        cin => cin,
        sum => sum,
        cout => cout
    );

    stimulus: process
    begin
        a <= '0';
        b <= '0';
        cin <= '0';
        wait for 10 ns;
        
        a <= '0';
        b <= '1';
        cin <= '0';
        wait for 10 ns;
        
        a <= '1';
        b <= '0';
        cin <= '0';
        wait for 10 ns;
        
        a <= '1';
        b <= '1';
        cin <= '0';
        wait for 10 ns;
        
        a <= '0';
        b <= '0';
        cin <= '1';
        wait for 10 ns;
        
        a <= '0';
        b <= '1';
        cin <= '1';
        wait for 10 ns;
        
        a <= '1';
        b <= '0';
        cin <= '1';
        wait for 10 ns;
        
        a <= '1';
        b <= '1';
        cin <= '1';
        wait for 10 ns;
        
        wait;
    end process;
end behavioral;

vhdl1/fa.vcd
$date
  Sat Feb 10 22:10:12 2024
$end
$version
  GHDL v0
$end
$timescale
  1 fs
$end
$scope module standard $end
$upscope $end
$scope module std_logic_1164 $end
$upscope $end
$scope module full_adder_tb $end
$var reg 1 ! a $end
$var reg 1 " b $end
$var reg 1 # cin $end
$var reg 1 $ sum $end
$var reg 1 % cout $end
$scope module uut $end
$var reg 1 & a $end
$var reg 1 ' b $end
$var reg 1 ( cin $end
$var reg 1 ) sum $end
$var reg 1 * cout $end
$upscope $end
$upscope $end
$enddefinitions $end
#0
0!
0"
0#
0$
0%
0&
0'
0(
0)
0*
#10000000
1"
1$
1'
1)
#20000000
1!
0"
1&
0'
#30000000
1"
0$
1%
1'
0)
1*
#40000000
0!
0"
1#
1$
0%
0&
0'
1(
1)
0*
#50000000
1"
0$
1%
1'
0)
1*
#60000000
1!
0"
1&
0'
#70000000
1"
1$
1'
1)
